agi_green/__init__.py
agi_green/agi_config_default.yaml
agi_green/agi_db.py
agi_green/chat_server.py
agi_green/config_namespace.py
agi_green/dict_namespace.py
agi_green/dispatcher.py
agi_green/docker-compose.yml
agi_green/protocol_azure.py
agi_green/protocol_cmd.py
agi_green/protocol_crew.py
agi_green/protocol_css.py
agi_green/protocol_email.py
agi_green/protocol_file.py
agi_green/protocol_form.py
agi_green/protocol_gpt.py
agi_green/protocol_http.py
agi_green/protocol_mq.py
agi_green/protocol_user.py
agi_green/protocol_ws.py
agi_green/rag.py
agi_green/utils.py
agi_green/wait_for_port.py
agi_green/frontend/dist/Tableau10-D7jGxypv.js
agi_green/frontend/dist/Tableau10-D7jGxypv.js.map
agi_green/frontend/dist/agi.green.css
agi_green/frontend/dist/agi.green.es.js
agi_green/frontend/dist/agi.green.es.js.map
agi_green/frontend/dist/agi.green.umd.js
agi_green/frontend/dist/agi.green.umd.js.map
agi_green/frontend/dist/arc-BtpVRodd.js
agi_green/frontend/dist/arc-BtpVRodd.js.map
agi_green/frontend/dist/array-CqVTtuYm.js
agi_green/frontend/dist/array-CqVTtuYm.js.map
agi_green/frontend/dist/blockDiagram-68f4deed-Dsn8asKO.js
agi_green/frontend/dist/blockDiagram-68f4deed-Dsn8asKO.js.map
agi_green/frontend/dist/c4Diagram-15b5d702-9NBZYn8F.js
agi_green/frontend/dist/c4Diagram-15b5d702-9NBZYn8F.js.map
agi_green/frontend/dist/channel-CFxlzmvY.js
agi_green/frontend/dist/channel-CFxlzmvY.js.map
agi_green/frontend/dist/chat.css
agi_green/frontend/dist/classDiagram-d40c83e7-DUNIbvqt.js
agi_green/frontend/dist/classDiagram-d40c83e7-DUNIbvqt.js.map
agi_green/frontend/dist/classDiagram-v2-d5a6b087-RUnbijkb.js
agi_green/frontend/dist/classDiagram-v2-d5a6b087-RUnbijkb.js.map
agi_green/frontend/dist/clone-BJzJ_cXB.js
agi_green/frontend/dist/clone-BJzJ_cXB.js.map
agi_green/frontend/dist/createText-d213de94-CpZb9VUz.js
agi_green/frontend/dist/createText-d213de94-CpZb9VUz.js.map
agi_green/frontend/dist/edges-332bd1c7-CEyRuwdV.js
agi_green/frontend/dist/edges-332bd1c7-CEyRuwdV.js.map
agi_green-0.4.8.dist-info/licenses/LICENSE
agi_green-0.4.8.dist-info/METADATA
agi_green-0.4.8.dist-info/WHEEL
agi_green-0.4.8.dist-info/top_level.txt
agi_green-0.4.8.dist-info/RECORD
