Metadata-Version: 2.4
Name: agi.green
Version: 0.4.8
Summary: AGI.green Framework
Author-email: Ken Seehart <ken@agi.green>
License: MIT License
Requires-Python: >=3.11
License-File: LICENSE
Requires-Dist: aiohttp
Requires-Dist: python-dotenv
Requires-Dist: openai<2.0.0,>=1.54.0
Requires-Dist: pyyaml>=6.0.2
Requires-Dist: redis
Requires-Dist: aiofiles~=24.1.0
Requires-Dist: aio_pika~=9.2.0
Requires-Dist: bcrypt
Requires-Dist: beanie>=2.0.0
Requires-Dist: aiosmtplib
Requires-Dist: markdown
Requires-Dist: ptvsd~=4.3.2
Requires-Dist: watchdog
Requires-Dist: tomli
Provides-Extra: dev
Requires-Dist: pytest; extra == "dev"
Requires-Dist: pytest-asyncio; extra == "dev"
Requires-Dist: black; extra == "dev"
Requires-Dist: isort; extra == "dev"
Dynamic: license-file
